LICENSE.txt
MANIFEST.in
README.rst
setup.py
rapidsms_multimodem/__init__.py
rapidsms_multimodem/models.py
rapidsms_multimodem/outgoing.py
rapidsms_multimodem/utils.py
rapidsms_multimodem/views.py
rapidsms_multimodem.egg-info/PKG-INFO
rapidsms_multimodem.egg-info/SOURCES.txt
rapidsms_multimodem.egg-info/dependency_links.txt
rapidsms_multimodem.egg-info/requires.txt
rapidsms_multimodem.egg-info/top_level.txt
rapidsms_multimodem/tests/__init__.py
rapidsms_multimodem/tests/test_outgoing.py
rapidsms_multimodem/tests/test_utils.py
rapidsms_multimodem/tests/test_views.py
rapidsms_multimodem/tests/urls.py